{
  "prepare_queue": {
    "installed": [],
    "uninstalled": []
  },
  "config_munge": {
    "files": {}
  },
  "installed_plugins": {
    "cordova-plugin-whitelist": {
      "PACKAGE_NAME": "com.algonquin.mad9022.giftr"
    },
    "cordova-plugin-device": {
      "PACKAGE_NAME": "com.algonquin.mad9022.giftr"
    },
    "cordova-plugin-inappbrowser": {
      "PACKAGE_NAME": "com.algonquin.mad9022.giftr"
    },
    "cordova-plugin-splashscreen": {
      "PACKAGE_NAME": "com.algonquin.mad9022.giftr"
    }
  },
  "dependent_plugins": {}
}